aiohttp_deps/__init__.py
aiohttp_deps/initializer.py
aiohttp_deps/keys.py
aiohttp_deps/py.typed
aiohttp_deps/router.py
aiohttp_deps/router.pyi
aiohttp_deps/swagger.py
aiohttp_deps/utils.py
aiohttp_deps/view.py
aiohttp_deps-1.1.4.dist-info/LICENSE
aiohttp_deps-1.1.4.dist-info/METADATA
aiohttp_deps-1.1.4.dist-info/WHEEL
aiohttp_deps-1.1.4.dist-info/RECORD
