Metadata-Version: 2.1
Name: aiohttp-deps
Version: 1.1.4
Summary: Dependency injection for AioHTTP
Home-page: https://github.com/taskiq-python/aiohttp-deps
License: LICENSE
Keywords: aiohttp,taskiq-dependencies
Author: Taskiq team
Author-email: taskiq@no-reply.com
Maintainer: Taskiq team
Maintainer-email: taskiq@no-reply.com
Requires-Python: >=3.9,<4.0
Classifier: Development Status :: 3 - Alpha
Classifier: Intended Audience :: Developers
Classifier: License :: Other/Proprietary License
Classifier: Operating System :: OS Independent
Classifier: Programming Language :: Python
Classifier: Programming Language :: Python :: 3
Classifier: Programming Language :: Python :: 3.9
Classifier: Programming Language :: Python :: 3.10
Classifier: Programming Language :: Python :: 3.11
Classifier: Programming Language :: Python :: 3.12
Classifier: Programming Language :: Python :: 3.13
Classifier: Programming Language :: Python :: 3 :: Only
Classifier: Programming Language :: Python :: 3.8
Classifier: Topic :: System :: Networking
Classifier: Typing :: Typed
Requires-Dist: aiohttp (>=3.9.0,<4)
Requires-Dist: deepmerge (>=2,<3)
Requires-Dist: pydantic (>=2,<3)
Requires-Dist: taskiq-dependencies (>=1.5.6,<2)
